{
  "__inputs": [
    {
      "name": "DS_INFLUXDB",
      "label": "InfluxDB",
      "description": "",
      "type": "datasource",
      "pluginId": "influxdb",
      "pluginName": "InfluxDB"
    }
  ],
  "__elements": {},
  "__requires": [
    {
      "type": "panel",
      "id": "gauge",
      "name": "Gauge",
      "version": ""
    },
    {
      "type": "grafana",
      "id": "grafana",
      "name": "Grafana",
      "version": "10.0.2"
    },
    {
      "type": "datasource",
      "id": "influxdb",
      "name": "InfluxDB",
      "version": "1.0.0"
    },
    {
      "type": "panel",
      "id": "piechart",
      "name": "Pie chart",
      "version": ""
    },
    {
      "type": "panel",
      "id": "stat",
      "name": "Stat",
      "version": ""
    },
    {
      "type": "panel",
      "id": "timeseries",
      "name": "Time series",
      "version": ""
    }
  ],
  "annotations": {
    "list": [
      {
        "builtIn": 1,
        "datasource": {
          "type": "grafana",
          "uid": "-- Grafana --"
        },
        "enable": true,
        "hide": true,
        "iconColor": "rgba(0, 211, 255, 1)",
        "name": "Annotations & Alerts",
        "type": "dashboard"
      }
    ]
  },
  "editable": true,
  "fiscalYearStartMonth": 0,
  "graphTooltip": 0,
  "id": null,
  "links": [],
  "liveNow": false,
  "panels": [
    {
      "gridPos": {
        "h": 1,
        "w": 24,
        "x": 0,
        "y": 0
      },
      "id": 11,
      "title": "Row title",
      "type": "row"
    },
    {
      "datasource": {
        "type": "influxdb",
        "uid": "${DS_INFLUXDB}"
      },
      "fieldConfig": {
        "defaults": {
          "color": {
            "mode": "thresholds"
          },
          "mappings": [],
          "thresholds": {
            "mode": "percentage",
            "steps": [
              {
                "color": "green",
                "value": null
              },
              {
                "color": "#EAB839",
                "value": 85
              },
              {
                "color": "red",
                "value": 95
              }
            ]
          },
          "unit": "percent"
        },
        "overrides": []
      },
      "gridPos": {
        "h": 8,
        "w": 4,
        "x": 0,
        "y": 1
      },
      "id": 1,
      "options": {
        "orientation": "auto",
        "reduceOptions": {
          "calcs": [
            "lastNotNull"
          ],
          "fields": "",
          "values": false
        },
        "showThresholdLabels": false,
        "showThresholdMarkers": true
      },
      "pluginVersion": "10.0.2",
      "targets": [
        {
          "alias": "CPU Use",
          "datasource": {
            "type": "influxdb",
            "uid": "${DS_INFLUXDB}"
          },
          "groupBy": [
            {
              "params": [
                "10s"
              ],
              "type": "time"
            },
            {
              "params": [
                "null"
              ],
              "type": "fill"
            }
          ],
          "measurement": "cpu",
          "orderByTime": "ASC",
          "policy": "autogen",
          "query": "SELECT mean(\"usage_system\") FROM \"autogen\".\"cpu\" WHERE (\"host\"::tag = 'NB-SVILUPPO99' AND \"cpu\"::tag = 'cpu-total') AND $timeFilter GROUP BY time(10s) fill(null)",
          "rawQuery": true,
          "refId": "A",
          "resultFormat": "time_series",
          "select": [
            [
              {
                "params": [
                  "usage_system"
                ],
                "type": "field"
              },
              {
                "params": [],
                "type": "mean"
              }
            ]
          ],
          "tags": [
            {
              "key": "host::tag",
              "operator": "=",
              "value": "NB-SVILUPPO99"
            },
            {
              "condition": "AND",
              "key": "cpu::tag",
              "operator": "=",
              "value": "cpu-total"
            }
          ]
        }
      ],
      "title": "CPU",
      "type": "gauge"
    },
    {
      "datasource": {
        "type": "influxdb",
        "uid": "${DS_INFLUXDB}"
      },
      "fieldConfig": {
        "defaults": {
          "color": {
            "mode": "palette-classic"
          },
          "custom": {
            "axisCenteredZero": false,
            "axisColorMode": "text",
            "axisLabel": "",
            "axisPlacement": "auto",
            "barAlignment": 0,
            "drawStyle": "line",
            "fillOpacity": 0,
            "gradientMode": "none",
            "hideFrom": {
              "legend": false,
              "tooltip": false,
              "viz": false
            },
            "lineInterpolation": "linear",
            "lineWidth": 1,
            "pointSize": 5,
            "scaleDistribution": {
              "type": "linear"
            },
            "showPoints": "auto",
            "spanNulls": false,
            "stacking": {
              "group": "A",
              "mode": "none"
            },
            "thresholdsStyle": {
              "mode": "line"
            }
          },
          "mappings": [],
          "max": 100,
          "min": 0,
          "thresholds": {
            "mode": "percentage",
            "steps": [
              {
                "color": "green",
                "value": null
              },
              {
                "color": "#EAB839",
                "value": 80
              },
              {
                "color": "red",
                "value": 95
              }
            ]
          }
        },
        "overrides": []
      },
      "gridPos": {
        "h": 8,
        "w": 8,
        "x": 4,
        "y": 1
      },
      "id": 8,
      "options": {
        "legend": {
          "calcs": [],
          "displayMode": "list",
          "placement": "bottom",
          "showLegend": true
        },
        "tooltip": {
          "mode": "single",
          "sort": "none"
        }
      },
      "targets": [
        {
          "alias": "CPU0",
          "datasource": {
            "type": "influxdb",
            "uid": "${DS_INFLUXDB}"
          },
          "groupBy": [
            {
              "params": [
                "10s"
              ],
              "type": "time"
            },
            {
              "params": [
                "linear"
              ],
              "type": "fill"
            }
          ],
          "measurement": "cpu",
          "orderByTime": "ASC",
          "policy": "autogen",
          "refId": "A",
          "resultFormat": "time_series",
          "select": [
            [
              {
                "params": [
                  "usage_system"
                ],
                "type": "field"
              },
              {
                "params": [],
                "type": "mean"
              }
            ]
          ],
          "tags": [
            {
              "key": "host::tag",
              "operator": "=",
              "value": "NB-SVILUPPO99"
            },
            {
              "condition": "AND",
              "key": "cpu::tag",
              "operator": "=",
              "value": "cpu0"
            }
          ]
        },
        {
          "alias": "CPU1",
          "datasource": {
            "type": "influxdb",
            "uid": "${DS_INFLUXDB}"
          },
          "groupBy": [
            {
              "params": [
                "10s"
              ],
              "type": "time"
            },
            {
              "params": [
                "linear"
              ],
              "type": "fill"
            }
          ],
          "hide": false,
          "measurement": "cpu",
          "orderByTime": "ASC",
          "policy": "autogen",
          "refId": "B",
          "resultFormat": "time_series",
          "select": [
            [
              {
                "params": [
                  "usage_system"
                ],
                "type": "field"
              },
              {
                "params": [],
                "type": "mean"
              }
            ]
          ],
          "tags": [
            {
              "key": "host::tag",
              "operator": "=",
              "value": "NB-SVILUPPO99"
            },
            {
              "condition": "AND",
              "key": "cpu::tag",
              "operator": "=",
              "value": "cpu1"
            }
          ]
        },
        {
          "alias": "CPU2",
          "datasource": {
            "type": "influxdb",
            "uid": "${DS_INFLUXDB}"
          },
          "groupBy": [
            {
              "params": [
                "10s"
              ],
              "type": "time"
            },
            {
              "params": [
                "linear"
              ],
              "type": "fill"
            }
          ],
          "hide": false,
          "measurement": "cpu",
          "orderByTime": "ASC",
          "policy": "autogen",
          "refId": "C",
          "resultFormat": "time_series",
          "select": [
            [
              {
                "params": [
                  "usage_system"
                ],
                "type": "field"
              },
              {
                "params": [],
                "type": "mean"
              }
            ]
          ],
          "tags": [
            {
              "key": "host::tag",
              "operator": "=",
              "value": "NB-SVILUPPO99"
            },
            {
              "condition": "AND",
              "key": "cpu::tag",
              "operator": "=",
              "value": "cpu2"
            }
          ]
        },
        {
          "alias": "CPU3",
          "datasource": {
            "type": "influxdb",
            "uid": "${DS_INFLUXDB}"
          },
          "groupBy": [
            {
              "params": [
                "10s"
              ],
              "type": "time"
            },
            {
              "params": [
                "linear"
              ],
              "type": "fill"
            }
          ],
          "hide": false,
          "measurement": "cpu",
          "orderByTime": "ASC",
          "policy": "autogen",
          "refId": "D",
          "resultFormat": "time_series",
          "select": [
            [
              {
                "params": [
                  "usage_system"
                ],
                "type": "field"
              },
              {
                "params": [],
                "type": "mean"
              }
            ]
          ],
          "tags": [
            {
              "key": "host::tag",
              "operator": "=",
              "value": "NB-SVILUPPO99"
            },
            {
              "condition": "AND",
              "key": "cpu::tag",
              "operator": "=",
              "value": "cpu3"
            }
          ]
        }
      ],
      "title": "Panel Title",
      "type": "timeseries"
    },
    {
      "datasource": {
        "type": "influxdb",
        "uid": "${DS_INFLUXDB}"
      },
      "fieldConfig": {
        "defaults": {
          "color": {
            "mode": "thresholds"
          },
          "mappings": [],
          "thresholds": {
            "mode": "percentage",
            "steps": [
              {
                "color": "green",
                "value": null
              },
              {
                "color": "#EAB839",
                "value": 80
              },
              {
                "color": "red",
                "value": 95
              }
            ]
          },
          "unit": "percent"
        },
        "overrides": []
      },
      "gridPos": {
        "h": 8,
        "w": 4,
        "x": 0,
        "y": 9
      },
      "id": 2,
      "options": {
        "orientation": "auto",
        "reduceOptions": {
          "calcs": [
            "lastNotNull"
          ],
          "fields": "/^Used$/",
          "values": false
        },
        "showThresholdLabels": false,
        "showThresholdMarkers": true
      },
      "pluginVersion": "10.0.2",
      "targets": [
        {
          "alias": "Used",
          "datasource": {
            "type": "influxdb",
            "uid": "${DS_INFLUXDB}"
          },
          "groupBy": [
            {
              "params": [
                "10s"
              ],
              "type": "time"
            },
            {
              "params": [
                "previous"
              ],
              "type": "fill"
            }
          ],
          "measurement": "mem",
          "orderByTime": "ASC",
          "policy": "autogen",
          "query": "SELECT mean(\"usage_system\") FROM \"autogen\".\"cpu\" WHERE (\"host\"::tag = 'NB-SVILUPPO99' AND \"cpu\"::tag = 'cpu-total') AND $timeFilter GROUP BY time(10s) fill(null)",
          "rawQuery": false,
          "refId": "A",
          "resultFormat": "time_series",
          "select": [
            [
              {
                "params": [
                  "used_percent"
                ],
                "type": "field"
              },
              {
                "params": [],
                "type": "distinct"
              }
            ]
          ],
          "tags": [
            {
              "key": "host::tag",
              "operator": "=",
              "value": "NB-SVILUPPO99"
            }
          ]
        }
      ],
      "title": "Memmory",
      "type": "gauge"
    },
    {
      "datasource": {
        "type": "influxdb",
        "uid": "${DS_INFLUXDB}"
      },
      "fieldConfig": {
        "defaults": {
          "color": {
            "mode": "palette-classic"
          },
          "custom": {
            "axisCenteredZero": false,
            "axisColorMode": "text",
            "axisLabel": "",
            "axisPlacement": "auto",
            "barAlignment": 0,
            "drawStyle": "line",
            "fillOpacity": 0,
            "gradientMode": "none",
            "hideFrom": {
              "legend": false,
              "tooltip": false,
              "viz": false
            },
            "lineInterpolation": "linear",
            "lineWidth": 1,
            "pointSize": 5,
            "scaleDistribution": {
              "type": "linear"
            },
            "showPoints": "auto",
            "spanNulls": false,
            "stacking": {
              "group": "A",
              "mode": "none"
            },
            "thresholdsStyle": {
              "mode": "dashed"
            }
          },
          "decimals": 0,
          "mappings": [],
          "max": 100,
          "min": 0,
          "thresholds": {
            "mode": "percentage",
            "steps": [
              {
                "color": "green",
                "value": null
              },
              {
                "color": "#EAB839",
                "value": 80
              },
              {
                "color": "red",
                "value": 95
              }
            ]
          },
          "unit": "percent"
        },
        "overrides": []
      },
      "gridPos": {
        "h": 8,
        "w": 8,
        "x": 4,
        "y": 9
      },
      "id": 9,
      "options": {
        "legend": {
          "calcs": [],
          "displayMode": "list",
          "placement": "bottom",
          "showLegend": true
        },
        "tooltip": {
          "mode": "single",
          "sort": "none"
        }
      },
      "targets": [
        {
          "alias": "Used",
          "datasource": {
            "type": "influxdb",
            "uid": "${DS_INFLUXDB}"
          },
          "groupBy": [
            {
              "params": [
                "$__interval"
              ],
              "type": "time"
            },
            {
              "params": [
                "linear"
              ],
              "type": "fill"
            }
          ],
          "measurement": "mem",
          "orderByTime": "ASC",
          "policy": "autogen",
          "refId": "A",
          "resultFormat": "time_series",
          "select": [
            [
              {
                "params": [
                  "used_percent"
                ],
                "type": "field"
              },
              {
                "params": [],
                "type": "mean"
              }
            ]
          ],
          "tags": [
            {
              "key": "host::tag",
              "operator": "=",
              "value": "NB-SVILUPPO99"
            }
          ]
        }
      ],
      "title": "Memmory",
      "type": "timeseries"
    },
    {
      "datasource": {
        "type": "influxdb",
        "uid": "${DS_INFLUXDB}"
      },
      "fieldConfig": {
        "defaults": {
          "color": {
            "mode": "palette-classic"
          },
          "custom": {
            "hideFrom": {
              "legend": false,
              "tooltip": false,
              "viz": false
            }
          },
          "mappings": [],
          "unit": "none"
        },
        "overrides": []
      },
      "gridPos": {
        "h": 8,
        "w": 4,
        "x": 0,
        "y": 17
      },
      "id": 5,
      "options": {
        "displayLabels": [],
        "legend": {
          "displayMode": "table",
          "placement": "bottom",
          "showLegend": true,
          "values": [
            "value",
            "percent"
          ]
        },
        "pieType": "pie",
        "reduceOptions": {
          "calcs": [
            "lastNotNull"
          ],
          "fields": "",
          "values": false
        },
        "tooltip": {
          "mode": "none",
          "sort": "none"
        }
      },
      "pluginVersion": "10.0.2",
      "targets": [
        {
          "alias": "Free",
          "datasource": {
            "type": "influxdb",
            "uid": "${DS_INFLUXDB}"
          },
          "groupBy": [
            {
              "params": [
                "10s"
              ],
              "type": "time"
            },
            {
              "params": [
                "null"
              ],
              "type": "fill"
            }
          ],
          "hide": false,
          "measurement": "disk",
          "orderByTime": "ASC",
          "policy": "autogen",
          "query": "SELECT mean(\"free\")/1073741824 FROM \"autogen\".\"disk\" WHERE (\"host\"::tag = 'NB-SVILUPPO99' AND \"device\"::tag = 'C:') AND $timeFilter GROUP BY time(10s) fill(null)",
          "rawQuery": true,
          "refId": "A",
          "resultFormat": "time_series",
          "select": [
            [
              {
                "params": [
                  "free"
                ],
                "type": "field"
              },
              {
                "params": [],
                "type": "mean"
              }
            ]
          ],
          "tags": [
            {
              "key": "host::tag",
              "operator": "=",
              "value": "NB-SVILUPPO99"
            },
            {
              "condition": "AND",
              "key": "device::tag",
              "operator": "=",
              "value": "C:"
            }
          ]
        },
        {
          "alias": "Used",
          "datasource": {
            "type": "influxdb",
            "uid": "${DS_INFLUXDB}"
          },
          "groupBy": [
            {
              "params": [
                "10s"
              ],
              "type": "time"
            },
            {
              "params": [
                "null"
              ],
              "type": "fill"
            }
          ],
          "hide": false,
          "measurement": "disk",
          "orderByTime": "ASC",
          "policy": "autogen",
          "query": "SELECT mean(\"used\")/1073741824 FROM \"autogen\".\"disk\" WHERE (\"host\"::tag = 'NB-SVILUPPO99' AND \"device\"::tag = 'C:') AND $timeFilter GROUP BY time(10s) fill(null)",
          "rawQuery": true,
          "refId": "B",
          "resultFormat": "time_series",
          "select": [
            [
              {
                "params": [
                  "used"
                ],
                "type": "field"
              },
              {
                "params": [],
                "type": "mean"
              }
            ]
          ],
          "tags": [
            {
              "key": "host::tag",
              "operator": "=",
              "value": "NB-SVILUPPO99"
            },
            {
              "condition": "AND",
              "key": "device::tag",
              "operator": "=",
              "value": "C:"
            }
          ]
        }
      ],
      "title": "Disk",
      "type": "piechart"
    },
    {
      "datasource": {
        "type": "influxdb",
        "uid": "${DS_INFLUXDB}"
      },
      "fieldConfig": {
        "defaults": {
          "color": {
            "mode": "thresholds"
          },
          "mappings": [],
          "max": 100,
          "min": 0,
          "thresholds": {
            "mode": "percentage",
            "steps": [
              {
                "color": "green",
                "value": null
              },
              {
                "color": "#EAB839",
                "value": 80
              },
              {
                "color": "red",
                "value": 95
              }
            ]
          },
          "unit": "percent"
        },
        "overrides": []
      },
      "gridPos": {
        "h": 4,
        "w": 8,
        "x": 4,
        "y": 17
      },
      "id": 4,
      "options": {
        "colorMode": "value",
        "graphMode": "area",
        "justifyMode": "auto",
        "orientation": "auto",
        "reduceOptions": {
          "calcs": [
            "lastNotNull"
          ],
          "fields": "",
          "values": false
        },
        "textMode": "auto"
      },
      "pluginVersion": "10.0.2",
      "targets": [
        {
          "datasource": {
            "type": "influxdb",
            "uid": "${DS_INFLUXDB}"
          },
          "groupBy": [
            {
              "params": [
                "$__interval"
              ],
              "type": "time"
            },
            {
              "params": [
                "previous"
              ],
              "type": "fill"
            }
          ],
          "measurement": "disk",
          "orderByTime": "ASC",
          "policy": "autogen",
          "refId": "A",
          "resultFormat": "time_series",
          "select": [
            [
              {
                "params": [
                  "used_percent"
                ],
                "type": "field"
              },
              {
                "params": [],
                "type": "mean"
              }
            ]
          ],
          "tags": [
            {
              "key": "host::tag",
              "operator": "=",
              "value": "NB-SVILUPPO99"
            }
          ]
        }
      ],
      "title": "Disk Space Usage",
      "type": "stat"
    },
    {
      "datasource": {
        "type": "influxdb",
        "uid": "${DS_INFLUXDB}"
      },
      "fieldConfig": {
        "defaults": {
          "color": {
            "mode": "thresholds"
          },
          "mappings": [],
          "max": 100,
          "min": 0,
          "thresholds": {
            "mode": "percentage",
            "steps": [
              {
                "color": "green",
                "value": null
              },
              {
                "color": "#EAB839",
                "value": 85
              },
              {
                "color": "red",
                "value": 90
              }
            ]
          },
          "unit": "percent"
        },
        "overrides": []
      },
      "gridPos": {
        "h": 4,
        "w": 8,
        "x": 4,
        "y": 21
      },
      "id": 3,
      "options": {
        "colorMode": "value",
        "graphMode": "area",
        "justifyMode": "auto",
        "orientation": "auto",
        "reduceOptions": {
          "calcs": [
            "lastNotNull"
          ],
          "fields": "",
          "values": false
        },
        "text": {},
        "textMode": "auto"
      },
      "pluginVersion": "10.0.2",
      "targets": [
        {
          "datasource": {
            "type": "influxdb",
            "uid": "${DS_INFLUXDB}"
          },
          "groupBy": [
            {
              "params": [
                "$__interval"
              ],
              "type": "time"
            },
            {
              "params": [
                "previous"
              ],
              "type": "fill"
            }
          ],
          "measurement": "swap",
          "orderByTime": "ASC",
          "policy": "autogen",
          "refId": "A",
          "resultFormat": "time_series",
          "select": [
            [
              {
                "params": [
                  "used_percent"
                ],
                "type": "field"
              },
              {
                "params": [],
                "type": "mean"
              }
            ]
          ],
          "tags": [
            {
              "key": "host::tag",
              "operator": "=",
              "value": "NB-SVILUPPO99"
            }
          ]
        }
      ],
      "title": "Swap",
      "type": "stat"
    }
  ],
  "refresh": "10s",
  "schemaVersion": 38,
  "style": "dark",
  "tags": [],
  "templating": {
    "list": []
  },
  "time": {
    "from": "now-5m",
    "to": "now"
  },
  "timepicker": {},
  "timezone": "",
  "title": "NB-SVILUPPO99",
  "uid": "ae9e84d0-78ea-4798-855e-3d3260e9fb2a",
  "version": 18,
  "weekStart": ""
}